CleanNumberPackage/Parser.py
CleanNumberPackage/__init__.py
CleanNumberPackage/tokenClass.py
CleanNumberPackage/tokenHandlerHelpers.py
CleanNumberPackage/tokenhandlers.py
CleanNumbersArmon-0.0.1.dist-info/METADATA
CleanNumbersArmon-0.0.1.dist-info/WHEEL
CleanNumbersArmon-0.0.1.dist-info/top_level.txt
CleanNumbersArmon-0.0.1.dist-info/RECORD
