Metadata-Version: 2.1
Name: CleanNumbersArmon
Version: 0.0.1
Summary: A small example package
Home-page: https://github.com/yourusername/mypackage
Author: Your Name
Author-email: Armon Barakchi <armon.barakchi@boeing.com>
Classifier: Programming Language :: Python :: 3
Classifier: Operating System :: OS Independent
Requires-Python: >=3.7
